LICENSE
MANIFEST.in
README.rst
setup.cfg
setup.py
itsbroken/__init__.py
itsbroken/testing.py
itsbroken/transaction.py
itsbroken/version.py
itsbroken.egg-info/PKG-INFO
itsbroken.egg-info/SOURCES.txt
itsbroken.egg-info/dependency_links.txt
itsbroken.egg-info/not-zip-safe
itsbroken.egg-info/top_level.txt