Metadata-Version: 1.0
Name: itsbroken
Version: 0.2
Summary: OpenERP Unittesting Toolkit
Home-page: https://github.com/openlabs/itsbroken/
Author: Openlabs Technologies & Consulting (P) Limited
Author-email: info@openlabs.co.in
License: GNU Affero General Public License v3
Platform: any
Classifier: Development Status :: 4 - Beta
Classifier: Environment :: Web Environment
Classifier: Intended Audience :: Developers
Classifier: License :: OSI Approved :: GNU Affero General Public License v3
Classifier: Operating System :: OS Independent
Classifier: Programming Language :: Python
Classifier: Topic :: Internet :: WWW/HTTP :: Dynamic Content
Classifier: Topic :: Software Development :: Libraries :: Python Modules
